openc3/__init__.py
openc3/__version__.py
openc3/accessors/__init__.py
openc3/accessors/accessor.py
openc3/accessors/binary_accessor.py
openc3/accessors/cbor_accessor.py
openc3/accessors/form_accessor.py
openc3/accessors/html_accessor.py
openc3/accessors/http_accessor.py
openc3/accessors/json_accessor.py
openc3/accessors/template_accessor.py
openc3/accessors/xml_accessor.py
openc3/api/__init__.py
openc3/api/api_shared.py
openc3/api/cmd_api.py
openc3/api/config_api.py
openc3/api/interface_api.py
openc3/api/limits_api.py
openc3/api/offline_access_api.py
openc3/api/router_api.py
openc3/api/settings_api.py
openc3/api/stash_api.py
openc3/api/target_api.py
openc3/api/tlm_api.py
openc3/bridge/bridge.py
openc3/bridge/bridge_config.py
openc3/bridge/bridge_interface_thread.py
openc3/bridge/bridge_router_thread.py
openc3/cli.py
openc3/config/__init__.py
openc3/config/config_parser.py
openc3/conversions/__init__.py
openc3/conversions/bit_reverse_conversion.py
openc3/conversions/conversion.py
openc3/conversions/generic_conversion.py
openc3/conversions/ip_read_conversion.py
openc3/conversions/ip_write_conversion.py
openc3/conversions/object_read_conversion.py
openc3/conversions/object_write_conversion.py
openc3/conversions/packet_time_formatted_conversion.py
openc3/conversions/packet_time_seconds_conversion.py
openc3/conversions/polynomial_conversion.py
openc3/conversions/processor_conversion.py
openc3/conversions/received_count_conversion.py
openc3/conversions/received_time_formatted_conversion.py
openc3/conversions/received_time_seconds_conversion.py
openc3/conversions/segmented_polynomial_conversion.py
openc3/conversions/unix_time_conversion.py
openc3/conversions/unix_time_formatted_conversion.py
openc3/conversions/unix_time_seconds_conversion.py
openc3/environment.py
openc3/interfaces/__init__.py
openc3/interfaces/file_interface.py
openc3/interfaces/http_client_interface.py
openc3/interfaces/http_server_interface.py
openc3/interfaces/interface.py
openc3-6.10.4.dist-info/METADATA
openc3-6.10.4.dist-info/WHEEL
openc3-6.10.4.dist-info/entry_points.txt
openc3-6.10.4.dist-info/licenses/LICENSE.txt
openc3-6.10.4.dist-info/RECORD
